{
    "1990": {
        "Agriculture": 4997830000,
        "Land-use change and forestry": 1909290000,
        "Waste": 1364400000,
        "Industry": 1010440000,
        "Manufacturing and construction": 3955390000,
        "Transport": 4609040000,
        "Electricity and heat": 8596170000,
        "Buildings": 2596850000,
        "Fugitive emissions": 2253380000,
        "Other fuel combustion": 1353120000,
        "Aviation and shipping": 630860000
    },
    "1991": {
        "Agriculture": 4988460000,
        "Land-use change and forestry": 1909290000,
        "Waste": 1395180000,
        "Industry": 1014310000,
        "Manufacturing and construction": 3875910000,
        "Transport": 4648550000,
        "Electricity and heat": 8735040000,
        "Buildings": 2622040000,
        "Fugitive emissions": 2261860000,
        "Other fuel combustion": 1362830000,
        "Aviation and shipping": 638250000
    },
    "1992": {
        "Agriculture": 4966820000,
        "Land-use change and forestry": 1909290000,
        "Waste": 1418280000,
        "Industry": 1030400000,
        "Manufacturing and construction": 3743480000,
        "Transport": 4753490000,
        "Electricity and heat": 8894600000,
        "Buildings": 2514520000,
        "Fugitive emissions": 2165360000,
        "Other fuel combustion": 1274100000,
        "Aviation and shipping": 675220000
    },
    "1993": {
        "Agriculture": 4936150000,
        "Land-use change and forestry": 1909290000,
        "Waste": 1444390000,
        "Industry": 1044440000,
        "Manufacturing and construction": 3694800000,
        "Transport": 4794310000,
        "Electricity and heat": 8945800000,
        "Buildings": 2574500000,
        "Fugitive emissions": 2129690000,
        "Other fuel combustion": 1293130000,
        "Aviation and shipping": 667470000
    },
    "1994": {
        "Agriculture": 4981350000,
        "Land-use change and forestry": 1909320000,
        "Waste": 1470960000,
        "Industry": 1151620000,
        "Manufacturing and construction": 3711410000,
        "Transport": 4891400000,
        "Electricity and heat": 9042500000,
        "Buildings": 2492940000,
        "Fugitive emissions": 2063050000,
        "Other fuel combustion": 1262920000,
        "Aviation and shipping": 693780000
    },
    "1995": {
        "Agriculture": 5038180000,
        "Land-use change and forestry": 1915150000,
        "Waste": 1476510000,
        "Industry": 1225100000,
        "Manufacturing and construction": 3937600000,
        "Transport": 5024900000,
        "Electricity and heat": 9231220000,
        "Buildings": 2566840000,
        "Fugitive emissions": 2073700000,
        "Other fuel combustion": 1214260000,
        "Aviation and shipping": 717670000
    },
    "1996": {
        "Agriculture": 5057350000,
        "Land-use change and forestry": 1711370000,
        "Waste": 1478310000,
        "Industry": 1277110000,
        "Manufacturing and construction": 3827310000,
        "Transport": 5232370000,
        "Electricity and heat": 9586390000,
        "Buildings": 2637750000,
        "Fugitive emissions": 2106340000,
        "Other fuel combustion": 1154630000,
        "Aviation and shipping": 739580000
    },
    "1997": {
        "Agriculture": 4986720000,
        "Land-use change and forestry": 2681330000,
        "Waste": 1474360000,
        "Industry": 1319750000,
        "Manufacturing and construction": 3852360000,
        "Transport": 5309680000,
        "Electricity and heat": 9853190000,
        "Buildings": 2615100000,
        "Fugitive emissions": 2091650000,
        "Other fuel combustion": 1203740000,
        "Aviation and shipping": 765100000
    },
    "1998": {
        "Agriculture": 5042290000,
        "Land-use change and forestry": 2011150000,
        "Waste": 1466280000,
        "Industry": 1323480000,
        "Manufacturing and construction": 3854060000,
        "Transport": 5431290000,
        "Electricity and heat": 10080660000,
        "Buildings": 2463090000,
        "Fugitive emissions": 2076100000,
        "Other fuel combustion": 1180800000,
        "Aviation and shipping": 789130000
    },
    "1999": {
        "Agriculture": 5098820000,
        "Land-use change and forestry": 1819850000,
        "Waste": 1464470000,
        "Industry": 1329140000,
        "Manufacturing and construction": 3694740000,
        "Transport": 5592430000,
        "Electricity and heat": 10134660000,
        "Buildings": 2533910000,
        "Fugitive emissions": 2089090000,
        "Other fuel combustion": 1191820000,
        "Aviation and shipping": 830320000
    },
    "2000": {
        "Agriculture": 5094120000,
        "Land-use change and forestry": 1670960000,
        "Waste": 1466760000,
        "Industry": 1388470000,
        "Manufacturing and construction": 3874930000,
        "Transport": 5770250000,
        "Electricity and heat": 10552870000,
        "Buildings": 2525960000,
        "Fugitive emissions": 2134250000,
        "Other fuel combustion": 1129160000,
        "Aviation and shipping": 855080000
    },
    "2001": {
        "Agriculture": 5105040000,
        "Land-use change and forestry": 1338220000,
        "Waste": 1452910000,
        "Industry": 1413160000,
        "Manufacturing and construction": 3897350000,
        "Transport": 5800870000,
        "Electricity and heat": 10813150000,
        "Buildings": 2550890000,
        "Fugitive emissions": 2179350000,
        "Other fuel combustion": 1150840000,
        "Aviation and shipping": 822920000
    },
    "2002": {
        "Agriculture": 5164050000,
        "Land-use change and forestry": 1853110000,
        "Waste": 1447970000,
        "Industry": 1479760000,
        "Manufacturing and construction": 3896220000,
        "Transport": 5951040000,
        "Electricity and heat": 10999870000,
        "Buildings": 2550130000,
        "Fugitive emissions": 2228840000,
        "Other fuel combustion": 1156850000,
        "Aviation and shipping": 861970000
    },
    "2003": {
        "Agriculture": 5158070000,
        "Land-use change and forestry": 1545550000,
        "Waste": 1443660000,
        "Industry": 1555420000,
        "Manufacturing and construction": 4083280000,
        "Transport": 6076410000,
        "Electricity and heat": 11617710000,
        "Buildings": 2633930000,
        "Fugitive emissions": 2319230000,
        "Other fuel combustion": 1184760000,
        "Aviation and shipping": 867410000
    },
    "2004": {
        "Agriculture": 5271690000,
        "Land-use change and forestry": 1909320000,
        "Waste": 1431880000,
        "Industry": 1654810000,
        "Manufacturing and construction": 4515140000,
        "Transport": 6358370000,
        "Electricity and heat": 12001490000,
        "Buildings": 2676430000,
        "Fugitive emissions": 2393240000,
        "Other fuel combustion": 1224790000,
        "Aviation and shipping": 946150000
    },
    "2005": {
        "Agriculture": 5307630000,
        "Land-use change and forestry": 1631340000,
        "Waste": 1422660000,
        "Industry": 1737330000,
        "Manufacturing and construction": 4927560000,
        "Transport": 6498620000,
        "Electricity and heat": 12373250000,
        "Buildings": 2676090000,
        "Fugitive emissions": 2481800000,
        "Other fuel combustion": 1243770000,
        "Aviation and shipping": 990800000
    },
    "2006": {
        "Agriculture": 5365470000,
        "Land-use change and forestry": 2005130000,
        "Waste": 1433850000,
        "Industry": 1868580000,
        "Manufacturing and construction": 5176290000,
        "Transport": 6649630000,
        "Electricity and heat": 12861970000,
        "Buildings": 2642410000,
        "Fugitive emissions": 2567020000,
        "Other fuel combustion": 1261320000,
        "Aviation and shipping": 1043570000
    },
    "2007": {
        "Agriculture": 5450030000,
        "Land-use change and forestry": 1471650000,
        "Waste": 1441860000,
        "Industry": 1993860000,
        "Manufacturing and construction": 5450180000,
        "Transport": 6856170000,
        "Electricity and heat": 13427330000,
        "Buildings": 2639530000,
        "Fugitive emissions": 2639990000,
        "Other fuel combustion": 1274020000,
        "Aviation and shipping": 1092580000
    },
    "2008": {
        "Agriculture": 5460100000,
        "Land-use change and forestry": 1432930000,
        "Waste": 1446930000,
        "Industry": 2039580000,
        "Manufacturing and construction": 5563140000,
        "Transport": 6862600000,
        "Electricity and heat": 13457770000,
        "Buildings": 2704710000,
        "Fugitive emissions": 2746400000,
        "Other fuel combustion": 1289810000,
        "Aviation and shipping": 1101740000
    },
    "2009": {
        "Agriculture": 5455290000,
        "Land-use change and forestry": 1825130000,
        "Waste": 1454290000,
        "Industry": 2089210000,
        "Manufacturing and construction": 5547260000,
        "Transport": 6724100000,
        "Electricity and heat": 13257850000,
        "Buildings": 2653970000,
        "Fugitive emissions": 2739150000,
        "Other fuel combustion": 1282790000,
        "Aviation and shipping": 1048500000
    },
    "2010": {
        "Agriculture": 5515230000,
        "Land-use change and forestry": 1490210000,
        "Waste": 1465130000,
        "Industry": 2223080000,
        "Manufacturing and construction": 6087720000,
        "Transport": 7011930000,
        "Electricity and heat": 14151170000,
        "Buildings": 2707440000,
        "Fugitive emissions": 2793840000,
        "Other fuel combustion": 1312840000,
        "Aviation and shipping": 1119390000
    },
    "2011": {
        "Agriculture": 5649500000,
        "Land-use change and forestry": 404680000,
        "Waste": 1467310000,
        "Industry": 2371510000,
        "Manufacturing and construction": 6313540000,
        "Transport": 7126580000,
        "Electricity and heat": 14755360000,
        "Buildings": 2654660000,
        "Fugitive emissions": 2830660000,
        "Other fuel combustion": 1317610000,
        "Aviation and shipping": 1134560000
    },
    "2012": {
        "Agriculture": 5677850000,
        "Land-use change and forestry": 432640000,
        "Waste": 1476630000,
        "Industry": 2450410000,
        "Manufacturing and construction": 6332910000,
        "Transport": 7182120000,
        "Electricity and heat": 15059190000,
        "Buildings": 2599000000,
        "Fugitive emissions": 2853290000,
        "Other fuel combustion": 1363570000,
        "Aviation and shipping": 1088430000
    },
    "2013": {
        "Agriculture": 5621260000,
        "Land-use change and forestry": 388260000,
        "Waste": 1484040000,
        "Industry": 2556160000,
        "Manufacturing and construction": 6324160000,
        "Transport": 7373420000,
        "Electricity and heat": 15320550000,
        "Buildings": 2712170000,
        "Fugitive emissions": 2860380000,
        "Other fuel combustion": 1406720000,
        "Aviation and shipping": 1095070000
    },
    "2014": {
        "Agriculture": 5669750000,
        "Land-use change and forestry": 737940000,
        "Waste": 1514260000,
        "Industry": 2671420000,
        "Manufacturing and construction": 6360380000,
        "Transport": 7498340000,
        "Electricity and heat": 15232520000,
        "Buildings": 2660700000,
        "Fugitive emissions": 2877380000,
        "Other fuel combustion": 1424610000,
        "Aviation and shipping": 1132170000
    },
    "2015": {
        "Agriculture": 5691560000,
        "Land-use change and forestry": 786460000,
        "Waste": 1543590000,
        "Industry": 2678620000,
        "Manufacturing and construction": 6315810000,
        "Transport": 7717010000,
        "Electricity and heat": 15009830000,
        "Buildings": 2689700000,
        "Fugitive emissions": 2883810000,
        "Other fuel combustion": 1444080000,
        "Aviation and shipping": 1184420000
    },
    "2016": {
        "Agriculture": 5737280000,
        "Land-use change and forestry": 1267610000,
        "Waste": 1560850000,
        "Industry": 2768080000,
        "Manufacturing and construction": 6188610000,
        "Transport": 7878140000,
        "Electricity and heat": 14949510000,
        "Buildings": 2737470000,
        "Fugitive emissions": 2889310000,
        "Other fuel combustion": 1437090000,
        "Aviation and shipping": 1225100000
    },
    "2017": {
        "Agriculture": 5821070000,
        "Land-use change and forestry": 1220050000,
        "Waste": 1583860000,
        "Industry": 2825880000,
        "Manufacturing and construction": 6174410000,
        "Transport": 8078450000,
        "Electricity and heat": 15167360000,
        "Buildings": 2796010000,
        "Fugitive emissions": 2879970000,
        "Other fuel combustion": 1443420000,
        "Aviation and shipping": 1280820000
    },
    "2018": {
        "Agriculture": 5817650000,
        "Land-use change and forestry": 1387560000,
        "Waste": 1606860000,
        "Industry": 2902680000,
        "Manufacturing and construction": 6158320000,
        "Transport": 8257730000,
        "Electricity and heat": 15590950000,
        "Buildings": 2882540000,
        "Fugitive emissions": 2883390000,
        "Other fuel combustion": 1452020000,
        "Aviation and shipping": 1311600000
    }
}